chessgui/__init__.py
chessgui-0.1.0.dist-info/METADATA
chessgui-0.1.0.dist-info/WHEEL
chessgui-0.1.0.dist-info/RECORD
