Metadata-Version: 2.1
Name: chessgui
Version: 0.1.0
Summary: 
Author: Piotr Żarczyński
Author-email: piotr.zarczynski.06@gmail.com
Requires-Python: >=3.11,<4.0
Classifier: Programming Language :: Python :: 3
Classifier: Programming Language :: Python :: 3.11
Classifier: Programming Language :: Python :: 3.12
Requires-Dist: chess (>=1.10.0,<2.0.0)
Requires-Dist: pygame (>=2.5.2,<3.0.0)
